LICENSE
MANIFEST.in
README.rst
setup.py
account/__init__.py
account/admin.py
account/apps.py
account/forms.py
account/models.py
account/tests.py
account/urls.py
account/views.py
account/migrations/0001_initial.py
account/migrations/0002_auto_20170313_1500.py
account/migrations/0003_auto_20170626_1213.py
account/migrations/__init__.py
account/static/css/bootstrap-theme.css
account/static/css/bootstrap-theme.css.map
account/static/css/bootstrap-theme.min.css
account/static/css/bootstrap-theme.min.css.map
account/static/css/bootstrap.css
account/static/css/bootstrap.css.map
account/static/css/bootstrap.min.css
account/static/css/bootstrap.min.css.map
account/static/css/font-awesome.css
account/static/css/font-awesome.min.css
account/static/css/style.css
account/static/fonts/FontAwesome.otf
account/static/fonts/fontawesome-webfont.eot
account/static/fonts/fontawesome-webfont.svg
account/static/fonts/fontawesome-webfont.ttf
account/static/fonts/fontawesome-webfont.woff
account/static/fonts/fontawesome-webfont.woff2
account/static/fonts/glyphicons-halflings-regular.eot
account/static/fonts/glyphicons-halflings-regular.svg
account/static/fonts/glyphicons-halflings-regular.ttf
account/static/fonts/glyphicons-halflings-regular.woff
account/static/fonts/glyphicons-halflings-regular.woff2
account/static/js/bootstrap.js
account/static/js/bootstrap.min.js
account/static/js/jquery-3.1.1.min.js
account/static/js/jquery-3.1.1.slim.min.js
account/static/js/jquery.easing.min.js
account/static/js/jquery.js
account/static/js/marked.min.js
account/static/js/npm.js
account/static/js/plugin.js
account/templates/Change_pass.html
account/templates/edit_profile.html
account/templates/editall.html
account/templates/logged_out.html
account/templates/login.html
account/templates/noprofile.html
account/templates/profile.html
account/templates/singup.html
account/templates/password/password_complete.html
account/templates/password/password_confirm.html
django_esay_account.egg-info/PKG-INFO
django_esay_account.egg-info/SOURCES.txt
django_esay_account.egg-info/dependency_links.txt
django_esay_account.egg-info/top_level.txt
